COPYING.txt
HISTORY.txt
MANIFEST.in
README.rst
setup.py
adao/__init__.py
adao/adaoBuilder.py
adao.egg-info/PKG-INFO
adao.egg-info/SOURCES.txt
adao.egg-info/dependency_links.txt
adao.egg-info/requires.txt
adao.egg-info/top_level.txt
adao/daAlgorithms/3DVAR.py
adao/daAlgorithms/4DVAR.py
adao/daAlgorithms/AdjointTest.py
adao/daAlgorithms/Blue.py
adao/daAlgorithms/ControledFunctionTest.py
adao/daAlgorithms/DerivativeFreeOptimization.py
adao/daAlgorithms/DifferentialEvolution.py
adao/daAlgorithms/EnsembleBlue.py
adao/daAlgorithms/EnsembleKalmanFilter.py
adao/daAlgorithms/EnsembleOfSimulationGenerationTask.py
adao/daAlgorithms/ExtendedBlue.py
adao/daAlgorithms/ExtendedKalmanFilter.py
adao/daAlgorithms/FunctionTest.py
adao/daAlgorithms/GradientTest.py
adao/daAlgorithms/InputValuesTest.py
adao/daAlgorithms/InterpolationByReducedModelTask.py
adao/daAlgorithms/InterpolationByReducedModelTest.py
adao/daAlgorithms/KalmanFilter.py
adao/daAlgorithms/LinearLeastSquares.py
adao/daAlgorithms/LinearityTest.py
adao/daAlgorithms/LocalSensitivityTest.py
adao/daAlgorithms/MeasurementsOptimalPositioningTask.py
adao/daAlgorithms/ModelicaCalibrationTask.py
adao/daAlgorithms/NonLinearLeastSquares.py
adao/daAlgorithms/ObservationSimulationComparisonTest.py
adao/daAlgorithms/ObserverTest.py
adao/daAlgorithms/ParallelFunctionTest.py
adao/daAlgorithms/ParameterCalibrationTask.py
adao/daAlgorithms/ParticleSwarmOptimization.py
adao/daAlgorithms/QuantileRegression.py
adao/daAlgorithms/ReducedModelingTest.py
adao/daAlgorithms/SamplingTest.py
adao/daAlgorithms/SimulatedAnnealing.py
adao/daAlgorithms/TabuSearch.py
adao/daAlgorithms/TangentTest.py
adao/daAlgorithms/UnscentedKalmanFilter.py
adao/daAlgorithms/__init__.py
adao/daAlgorithms/Atoms/__init__.py
adao/daAlgorithms/Atoms/ceks.py
adao/daAlgorithms/Atoms/ecw2ukf.py
adao/daAlgorithms/Atoms/ecwapso.py
adao/daAlgorithms/Atoms/ecwblue.py
adao/daAlgorithms/Atoms/ecwcekf.py
adao/daAlgorithms/Atoms/ecwdeim.py
adao/daAlgorithms/Atoms/ecwdfo.py
adao/daAlgorithms/Atoms/ecwdgsa.py
adao/daAlgorithms/Atoms/ecweim.py
adao/daAlgorithms/Atoms/ecwexblue.py
adao/daAlgorithms/Atoms/ecwexkf.py
