Metadata-Version: 2.4
Name: adao
Version: 9.15.0.2
Summary: ADAO: A module for Data Assimilation and Optimization
Home-page: http://www.salome-platform.org/
Author: Jean-Philippe Argaud
Author-email: jean-philippe.argaud@edf.fr
License: GNU Library or Lesser General Public License (LGPL)
Keywords: optimization,data assimilation,calibration,interpolation,reduction,inverse problem,tunning,sampling,minimization,black-box,checking,3D-Var,4D-Var,Filtering,Kalman,Ensemble,Regression,Quantile,V&V,Tabu Search,BLUE,EnKF,Ensemble Kalman Filter,PSO,Particle Swarm Optimization,UKF,Unscented Kalman Filter,Least Squares,Unscented,ROM,RBM,EIM,DEIM,POD,DFO,Derivative Free Optimization,Swarm,Optimal Positioning,Gradient Test,Adjoint Test,Sensitivity,Quantile Regression
Classifier: Programming Language :: Python
Classifier: Programming Language :: Python :: 3
Classifier: Development Status :: 5 - Production/Stable
Classifier: Environment :: Other Environment
Classifier: Intended Audience :: Developers
Classifier: Operating System :: Microsoft :: Windows
Classifier: Operating System :: Unix
Classifier: Operating System :: MacOS :: MacOS X
Classifier: Operating System :: OS Independent
Classifier: Topic :: Scientific/Engineering
Classifier: Topic :: Scientific/Engineering :: Mathematics
Classifier: Topic :: Software Development :: Libraries
Classifier: Topic :: Software Development :: Libraries :: Python Modules
Requires-Python: >=3.6
License-File: COPYING.txt
Requires-Dist: numpy
Requires-Dist: scipy
Dynamic: author
Dynamic: author-email
Dynamic: classifier
Dynamic: description
Dynamic: description-content-type
Dynamic: home-page
Dynamic: keywords
Dynamic: license
Dynamic: license-file
Dynamic: requires-dist
Dynamic: requires-python
Dynamic: summary
